dbt/adapters/odps/__init__.py
dbt/adapters/odps/__version__.py
dbt/adapters/odps/column.py
dbt/adapters/odps/connections.py
dbt/adapters/odps/context.py
dbt/adapters/odps/credentials.py
dbt/adapters/odps/date.py
dbt/adapters/odps/impl.py
dbt/adapters/odps/relation.py
dbt/adapters/odps/setting_parser.py
dbt/adapters/odps/utils.py
dbt/adapters/odps/wrapper.py
dbt/adapters/odps/relation_configs/__init__.py
dbt/adapters/odps/relation_configs/_base.py
dbt/adapters/odps/relation_configs/_materialized_view.py
dbt/adapters/odps/relation_configs/_partition.py
dbt/adapters/odps/relation_configs/_policies.py
dbt/include/odps/__init__.py
dbt/include/odps/dbt_project.yml
dbt/include/odps/macros.yml
dbt/include/odps/profile_template.yml
dbt/include/odps/macros/adapters.sql
dbt/include/odps/macros/adapters/apply_grants.sql
dbt/include/odps/macros/adapters/columns.sql
dbt/include/odps/macros/adapters/persist_docs.sql
dbt/include/odps/macros/materializations/clone.sql
dbt/include/odps/macros/materializations/hooks.sql
dbt/include/odps/macros/materializations/raw.sql
dbt/include/odps/macros/materializations/incremental/incremental.sql
dbt/include/odps/macros/materializations/incremental/merge.sql
dbt/include/odps/macros/materializations/incremental/incremental_strategy/insert_overwrite.sql
dbt/include/odps/macros/materializations/incremental/incremental_strategy/microbatch.sql
dbt/include/odps/macros/materializations/seeds/seeds.sql
dbt/include/odps/macros/materializations/snapshots/snapshot.sql
dbt/include/odps/macros/relations/partition.sql
dbt/include/odps/macros/relations/materialized_view/alter.sql
dbt/include/odps/macros/relations/materialized_view/create.sql
dbt/include/odps/macros/relations/materialized_view/drop.sql
dbt/include/odps/macros/relations/materialized_view/refresh.sql
dbt/include/odps/macros/relations/materialized_view/rename.sql
dbt/include/odps/macros/relations/materialized_view/replace.sql
dbt/include/odps/macros/relations/table/create.sql
dbt_odps_winwin-1.9.0.dist-info/METADATA
dbt_odps_winwin-1.9.0.dist-info/WHEEL
dbt_odps_winwin-1.9.0.dist-info/licenses/LICENSE
dbt_odps_winwin-1.9.0.dist-info/RECORD
