Metadata-Version: 2.4
Name: dbt-odps-winwin
Version: 1.9.0
Summary: The ODPS(MaxCompute) adapter plugin for dbt
Author-email: Winwin Inc <dev@brandct.com>
Maintainer-email: Winwin Inc <dev@brandct.com>
License-File: LICENSE
Keywords: MaxCompute,adapter,adapters,aliyun,database,dbt,dbt Cloud,dbt Core,dbt Labs,dbt-core,elt,odps
Classifier: Development Status :: 5 - Production/Stable
Classifier: License :: OSI Approved :: Apache Software License
Classifier: Operating System :: MacOS :: MacOS X
Classifier: Operating System :: Microsoft :: Windows
Classifier: Operating System :: POSIX :: Linux
Classifier: Programming Language :: Python :: 3.9
Classifier: Programming Language :: Python :: 3.10
Classifier: Programming Language :: Python :: 3.11
Classifier: Programming Language :: Python :: 3.12
Requires-Python: >=3.9.0
Requires-Dist: dbt-adapters<2.0,>=1.7
Requires-Dist: dbt-common<2.0,>=1.10
Requires-Dist: dbt-core>=1.8.0
Requires-Dist: pandas>=2.2.3
Requires-Dist: pyodps>=0.12.2.2
Requires-Dist: pytest-dotenv>=0.5.2
